README.md
setup.py
ISAT_SAM_BACKEND/__init__.py
ISAT_SAM_BACKEND/config.py
ISAT_SAM_BACKEND/main.py
ISAT_SAM_BACKEND/model.py
ISAT_SAM_BACKEND/api/__init__.py
ISAT_SAM_BACKEND/api/v1/__init__.py
ISAT_SAM_BACKEND/api/v1/routers.py
ISAT_SAM_BACKEND/api/v1/endpoints/api.py
ISAT_SAM_BACKEND/api/v1/endpoints/pages.py
ISAT_SAM_BACKEND/checkpoints/mobile_sam.pt
ISAT_SAM_BACKEND/segment_any/gpu_resource.py
ISAT_SAM_BACKEND/segment_any/model_zoo.py
ISAT_SAM_BACKEND/segment_any/segment_any.py
ISAT_SAM_BACKEND/segment_any/edge_sam/__init__.py
ISAT_SAM_BACKEND/segment_any/edge_sam/automatic_mask_generator.py
ISAT_SAM_BACKEND/segment_any/edge_sam/build_sam.py
ISAT_SAM_BACKEND/segment_any/edge_sam/predictor.py
ISAT_SAM_BACKEND/segment_any/edge_sam/modeling/__init__.py
ISAT_SAM_BACKEND/segment_any/edge_sam/modeling/common.py
ISAT_SAM_BACKEND/segment_any/edge_sam/modeling/image_encoder.py
ISAT_SAM_BACKEND/segment_any/edge_sam/modeling/mask_decoder.py
ISAT_SAM_BACKEND/segment_any/edge_sam/modeling/prompt_encoder.py
ISAT_SAM_BACKEND/segment_any/edge_sam/modeling/rep_vit.py
ISAT_SAM_BACKEND/segment_any/edge_sam/modeling/sam.py
ISAT_SAM_BACKEND/segment_any/edge_sam/modeling/transformer.py
ISAT_SAM_BACKEND/segment_any/edge_sam/onnx/__init__.py
ISAT_SAM_BACKEND/segment_any/edge_sam/onnx/predictor_onnx.py
ISAT_SAM_BACKEND/segment_any/edge_sam/utils/__init__.py
ISAT_SAM_BACKEND/segment_any/edge_sam/utils/amg.py
ISAT_SAM_BACKEND/segment_any/edge_sam/utils/coreml.py
ISAT_SAM_BACKEND/segment_any/edge_sam/utils/transforms.py
ISAT_SAM_BACKEND/segment_any/mobile_sam/__init__.py
ISAT_SAM_BACKEND/segment_any/mobile_sam/automatic_mask_generator.py
ISAT_SAM_BACKEND/segment_any/mobile_sam/build_sam.py
ISAT_SAM_BACKEND/segment_any/mobile_sam/predictor.py
ISAT_SAM_BACKEND/segment_any/mobile_sam/modeling/__init__.py
ISAT_SAM_BACKEND/segment_any/mobile_sam/modeling/common.py
ISAT_SAM_BACKEND/segment_any/mobile_sam/modeling/image_encoder.py
ISAT_SAM_BACKEND/segment_any/mobile_sam/modeling/mask_decoder.py
isat_sam_backend.egg-info/PKG-INFO
isat_sam_backend.egg-info/SOURCES.txt
isat_sam_backend.egg-info/dependency_links.txt
isat_sam_backend.egg-info/entry_points.txt
isat_sam_backend.egg-info/requires.txt
isat_sam_backend.egg-info/top_level.txt