Metadata-Version: 2.4
Name: isat-sam-backend
Version: 1.0.1
Summary: ISAT SAM encoding backend.
Home-page: https://github.com/yatengLG/ISAT_with_segment_anything
Author: yatengLG
Author-email: yatenglg@foxmail.com
License: Apache2.0
Keywords: annotation tool,segment anything,image annotation,semantic segmentation,instance segmentation
Classifier: Intended Audience :: Developers
Classifier: Intended Audience :: Science/Research
Classifier: Development Status :: 5 - Production/Stable
Classifier: Natural Language :: Chinese (Simplified)
Classifier: Natural Language :: English
Classifier: License :: OSI Approved :: Apache Software License
Classifier: Operating System :: OS Independent
Classifier: Programming Language :: Python
Classifier: Programming Language :: Python :: 3.8
Classifier: Programming Language :: Python :: 3.9
Classifier: Programming Language :: Python :: 3.10
Requires-Python: >=3.8
Requires-Dist: fastapi
Requires-Dist: python-multipart
Requires-Dist: uvicorn
Requires-Dist: torch>=2.1.1
Requires-Dist: torchvision
Requires-Dist: timm
Requires-Dist: hydra-core>=1.3.2
Requires-Dist: tqdm>=4.66.1
Requires-Dist: iopath
Requires-Dist: tqdm
Requires-Dist: tabulate
Requires-Dist: requests
Dynamic: author
Dynamic: author-email
Dynamic: classifier
Dynamic: description
Dynamic: description-content-type
Dynamic: home-page
Dynamic: keywords
Dynamic: license
Dynamic: requires-dist
Dynamic: requires-python
Dynamic: summary
